osym/rpc/__init__.py
osym/rpc/node.py
osym_rpc-0.1.4.dist-info/METADATA
osym_rpc-0.1.4.dist-info/WHEEL
osym_rpc-0.1.4.dist-info/top_level.txt
osym_rpc-0.1.4.dist-info/RECORD
